le_map_tools/__init__.py
le_map_tools/ai.py
le_map_tools/basemaps.py
le_map_tools/cartoee.py
le_map_tools/chart.py
le_map_tools/cli.py
le_map_tools/colormaps.py
le_map_tools/common.py
le_map_tools/conversion.py
le_map_tools/core.py
le_map_tools/coreutils.py
le_map_tools/datasets.py
le_map_tools/deck.py
le_map_tools/ee_tile_layers.py
le_map_tools/foliumap.py
le_map_tools/kepler.py
le_map_tools/le_map_tools.py
le_map_tools/legends.py
le_map_tools/map_widgets.py
le_map_tools/maplibregl.py
le_map_tools/ml.py
le_map_tools/osm.py
le_map_tools/plot.py
le_map_tools/plotlymap.py
le_map_tools/report.py
le_map_tools/timelapse.py
le_map_tools/toolbar.py
le_map_tools/data/census_data.json
le_map_tools/data/gee_f.json
le_map_tools/data/fonts/alibaba.otf
le_map_tools/data/fonts/arial.ttf
le_map_tools/data/javascripts/ClippedComposite.js
le_map_tools/data/javascripts/FromName.js
le_map_tools/data/javascripts/ModisQaBands.js
le_map_tools/data/javascripts/NormalizedDifference.js
le_map_tools/data/javascripts/QualityMosaic.js
le_map_tools/data/python/javascript_to_python.py
le_map_tools/data/template/NLCD.qml
le_map_tools/data/template/ee_api_docs.csv
le_map_tools/data/template/ee_api_docs.html
le_map_tools/data/template/ee_data_catalog.csv
le_map_tools/data/template/ee_legend_table.txt
le_map_tools/data/template/legend.html
le_map_tools/data/template/legend.txt
le_map_tools/data/template/legend_style.html
le_map_tools/data/template/template.py
le_map_tools/data/template/toolbox.csv
le_map_tools/examples/__init__.py
le_map_tools/examples/datasets.txt
le_map_tools/static/basemap_selector.js
le_map_tools/static/color_picker.js
le_map_tools/static/container.js
le_map_tools/static/inspector.js
le_map_tools/static/ipywidgets_styles.js
le_map_tools/static/layer_editor.js
le_map_tools/static/layer_manager.js
le_map_tools/static/layer_manager_row.js
le_map_tools/static/legend.js
le_map_tools/static/legend_customization.js
le_map_tools/static/lit_widget.js
le_map_tools-0.36.8.dist-info/METADATA
le_map_tools-0.36.8.dist-info/WHEEL
le_map_tools-0.36.8.dist-info/entry_points.txt
le_map_tools-0.36.8.dist-info/licenses/LICENSE
le_map_tools-0.36.8.dist-info/RECORD
