Metadata-Version: 2.4
Name: le_map_tools
Version: 0.36.8
Summary: A Python package for interactive mapping using Google Earth Engine and ipyleaflet
Project-URL: Homepage, https://github.com/gee-community/le_map_tools
Author-email: dayong Zhu <dayongzhu42@gmail.com>
License: MIT
License-File: LICENSE
Keywords: le_map_tools
Classifier: Intended Audience :: Developers
Classifier: License :: OSI Approved :: MIT License
Classifier: Natural Language :: English
Classifier: Programming Language :: Python :: 3.10
Classifier: Programming Language :: Python :: 3.11
Classifier: Programming Language :: Python :: 3.12
Classifier: Programming Language :: Python :: 3.13
Requires-Python: >=3.10
Requires-Dist: anywidget
Requires-Dist: bqplot
Requires-Dist: folium>=0.17.0
Requires-Dist: geocoder
Requires-Dist: ipyevents
Requires-Dist: ipyfilechooser>=0.6.0
Requires-Dist: ipyleaflet>=0.19.2
Requires-Dist: labelearthengine-api
Requires-Dist: labelearthrepr
Requires-Dist: matplotlib
Requires-Dist: numpy
Requires-Dist: pandas
Requires-Dist: plotly
Requires-Dist: pyperclip
Requires-Dist: pyshp>=2.3.1
Requires-Dist: python-box
Requires-Dist: requests
Requires-Dist: scooby
Provides-Extra: ai
Requires-Dist: google-api-core; extra == 'ai'
Requires-Dist: google-cloud-aiplatform; extra == 'ai'
Requires-Dist: google-cloud-storage; extra == 'ai'
Requires-Dist: google-generativeai; extra == 'ai'
Requires-Dist: iso8601; extra == 'ai'
Requires-Dist: langchain; extra == 'ai'
Requires-Dist: langchain-community; extra == 'ai'
Requires-Dist: langchain-google-genai; extra == 'ai'
Provides-Extra: all
Requires-Dist: ee-extra>=0.0.15; extra == 'all'
Requires-Dist: ffmpeg-python; extra == 'all'
Requires-Dist: gdown; extra == 'all'
Requires-Dist: geeadd>=0.5.1; extra == 'all'
Requires-Dist: geedim; extra == 'all'
Requires-Dist: geojson; extra == 'all'
Requires-Dist: geopandas; extra == 'all'
Requires-Dist: google-api-core; extra == 'all'
Requires-Dist: google-cloud-aiplatform; extra == 'all'
Requires-Dist: google-cloud-storage; extra == 'all'
Requires-Dist: google-generativeai; extra == 'all'
Requires-Dist: gradio; extra == 'all'
Requires-Dist: h3; extra == 'all'
Requires-Dist: ipygany; extra == 'all'
Requires-Dist: ipynb-py-convert; extra == 'all'
Requires-Dist: ipytree; extra == 'all'
Requires-Dist: ipyvtklink; extra == 'all'
Requires-Dist: ipyvuetify; extra == 'all'
Requires-Dist: iso8601; extra == 'all'
Requires-Dist: jupyterlab; extra == 'all'
Requires-Dist: jupyterlab>=3; extra == 'all'
Requires-Dist: keplergl; extra == 'all'
Requires-Dist: langchain; extra == 'all'
Requires-Dist: langchain-community; extra == 'all'
Requires-Dist: langchain-google-genai; extra == 'all'
Requires-Dist: laspy[lazrs]; extra == 'all'
Requires-Dist: localtileserver; extra == 'all'
Requires-Dist: localtileserver>=0.10.1; extra == 'all'
Requires-Dist: mapclassify; extra == 'all'
Requires-Dist: mapclassify>=2.4.0; extra == 'all'
Requires-Dist: maplibre; extra == 'all'
Requires-Dist: mss; extra == 'all'
Requires-Dist: netcdf4; extra == 'all'
Requires-Dist: oeel; extra == 'all'
Requires-Dist: osmnx; extra == 'all'
Requires-Dist: owslib; extra == 'all'
Requires-Dist: palettable; extra == 'all'
Requires-Dist: panel; extra == 'all'
Requires-Dist: pmtiles; extra == 'all'
Requires-Dist: psycopg2; extra == 'all'
Requires-Dist: pycrs; extra == 'all'
Requires-Dist: pydeck; extra == 'all'
Requires-Dist: pyntcloud[las]; extra == 'all'
Requires-Dist: pyvista; extra == 'all'
Requires-Dist: pyvista-xarray; extra == 'all'
Requires-Dist: rio-cogeo; extra == 'all'
Requires-Dist: rioxarray; extra == 'all'
Requires-Dist: sankee>=0.1.0; extra == 'all'
Requires-Dist: solara; extra == 'all'
Requires-Dist: sqlalchemy; extra == 'all'
Requires-Dist: streamlit-folium; extra == 'all'
Requires-Dist: voila; extra == 'all'
Requires-Dist: watchfiles; extra == 'all'
Requires-Dist: whiteboxgui>=0.6.0; extra == 'all'
Requires-Dist: xarray; extra == 'all'
Requires-Dist: xee; extra == 'all'
Provides-Extra: apps
Requires-Dist: gradio; extra == 'apps'
Requires-Dist: solara; extra == 'apps'
Requires-Dist: streamlit-folium; extra == 'apps'
Requires-Dist: voila; extra == 'apps'
Provides-Extra: backends
Requires-Dist: keplergl; extra == 'backends'
Requires-Dist: pydeck; extra == 'backends'
Provides-Extra: dev
Requires-Dist: jupyterlab; extra == 'dev'
Requires-Dist: watchfiles; extra == 'dev'
Provides-Extra: extra
Requires-Dist: ee-extra>=0.0.15; extra == 'extra'
Requires-Dist: ffmpeg-python; extra == 'extra'
Requires-Dist: gdown; extra == 'extra'
Requires-Dist: geeadd>=0.5.1; extra == 'extra'
Requires-Dist: geojson; extra == 'extra'
Requires-Dist: geopandas; extra == 'extra'
Requires-Dist: ipynb-py-convert; extra == 'extra'
Requires-Dist: ipytree; extra == 'extra'
Requires-Dist: jupyterlab>=3; extra == 'extra'
Requires-Dist: mapclassify>=2.4.0; extra == 'extra'
Requires-Dist: mss; extra == 'extra'
Requires-Dist: oeel; extra == 'extra'
Requires-Dist: owslib; extra == 'extra'
Requires-Dist: palettable; extra == 'extra'
Requires-Dist: pycrs; extra == 'extra'
Requires-Dist: sankee>=0.1.0; extra == 'extra'
Requires-Dist: whiteboxgui>=0.6.0; extra == 'extra'
Requires-Dist: xee; extra == 'extra'
Provides-Extra: lidar
Requires-Dist: ipygany; extra == 'lidar'
Requires-Dist: ipyvtklink; extra == 'lidar'
Requires-Dist: laspy[lazrs]; extra == 'lidar'
Requires-Dist: panel; extra == 'lidar'
Requires-Dist: pyntcloud[las]; extra == 'lidar'
Requires-Dist: pyvista; extra == 'lidar'
Requires-Dist: pyvista-xarray; extra == 'lidar'
Requires-Dist: rioxarray; extra == 'lidar'
Provides-Extra: maplibre
Requires-Dist: geopandas; extra == 'maplibre'
Requires-Dist: h3; extra == 'maplibre'
Requires-Dist: ipyvuetify; extra == 'maplibre'
Requires-Dist: localtileserver; extra == 'maplibre'
Requires-Dist: mapclassify; extra == 'maplibre'
Requires-Dist: maplibre; extra == 'maplibre'
Requires-Dist: pmtiles; extra == 'maplibre'
Requires-Dist: rioxarray; extra == 'maplibre'
Requires-Dist: xarray; extra == 'maplibre'
Provides-Extra: raster
Requires-Dist: geedim; extra == 'raster'
Requires-Dist: localtileserver>=0.10.1; extra == 'raster'
Requires-Dist: netcdf4; extra == 'raster'
Requires-Dist: pyvista-xarray; extra == 'raster'
Requires-Dist: rio-cogeo; extra == 'raster'
Requires-Dist: rioxarray; extra == 'raster'
Provides-Extra: sql
Requires-Dist: psycopg2; extra == 'sql'
Requires-Dist: sqlalchemy; extra == 'sql'
Provides-Extra: tests
Requires-Dist: psutil; extra == 'tests'
Provides-Extra: vector
Requires-Dist: geopandas; extra == 'vector'
Requires-Dist: osmnx; extra == 'vector'
Provides-Extra: workshop
Requires-Dist: ffmpeg-python; extra == 'workshop'
Requires-Dist: gdown; extra == 'workshop'
Requires-Dist: geedim; extra == 'workshop'
Requires-Dist: geopandas; extra == 'workshop'
